terminal_s/__init__.py
terminal_s/__main__.py
terminal_s/terminal.py
terminal_s-0.2.0.dist-info/METADATA
terminal_s-0.2.0.dist-info/WHEEL
terminal_s-0.2.0.dist-info/entry_points.txt
terminal_s-0.2.0.dist-info/top_level.txt
terminal_s-0.2.0.dist-info/zip-safe
terminal_s-0.2.0.dist-info/RECORD
