Metadata-Version: 2.1
Name: terminal-s
Version: 0.2.0
Summary: A super simple serial terminal
Home-page: https://github.com/makerdiary/terminal-s
Author: Yihui Xiong
Author-email: yihui.xiong@hotmail.com
License: UNKNOWN
Platform: UNKNOWN
Requires-Dist: pyserial
Requires-Dist: colorama
Requires-Dist: click
